Metadata-Version: 2.1
Name: watermark-remover-cli
Version: 0.0.1
Summary: Watermark Remover for PDFs and Images
Home-page: https://github.com/Mupati/watermark_remover_cli
Author: Kofi Mupati
Author-email: scientificgh@gmail.com
License: UNKNOWN
Platform: UNKNOWN
Classifier: Programming Language :: Python :: 3
Classifier: License :: OSI Approved :: MIT License
Classifier: Operating System :: OS Independent
Requires-Python: >=3.8
